CHANGES.rst
basicserial/__init__.py
basicserial/json.py
basicserial/toml.py
basicserial/util.py
basicserial/yaml.py
basicserial-1.2.1.dist-info/LICENSE.rst
basicserial-1.2.1.dist-info/WHEEL
basicserial-1.2.1.dist-info/METADATA
basicserial-1.2.1.dist-info/RECORD
