Metadata-Version: 2.1
Name: basicserial
Version: 1.2.1
Summary: A convenience wrapper around serialization libraries to handle common tasks.
Home-page: https://github.com/jayclassless/basicserial
License: MIT
Keywords: serialize,serialization,json,yaml,toml
Author: Jason Simeone
Author-email: jay@classless.net
Requires-Python: >=3.6,<4.0
Classifier: Development Status :: 5 - Production/Stable
Classifier: License :: OSI Approved :: MIT License
Classifier: Programming Language :: Python :: 3
Classifier: Programming Language :: Python :: 3.6
Classifier: Programming Language :: Python :: 3.7
Classifier: Programming Language :: Python :: 3.8
Classifier: Programming Language :: Python :: 3.9
Requires-Dist: iso8601
